ecranner/__init__.py
ecranner/cli.py
ecranner/config/config.py
ecranner/config/exceptions.py
ecranner/config/schema_1.0.json
ecranner/config/validate.py
ecranner/docker.py
ecranner/ecr.py
ecranner/ecranner.py
ecranner/exceptions.py
ecranner/log.py
ecranner/slack.py
ecranner/trivy.py
ecranner/utils.py
ecranner-0.0.2.dist-info/entry_points.txt
ecranner-0.0.2.dist-info/LICENSE
ecranner-0.0.2.dist-info/WHEEL
ecranner-0.0.2.dist-info/METADATA
ecranner-0.0.2.dist-info/RECORD
