Metadata-Version: 2.1
Name: ecranner
Version: 0.0.2
Summary: Scan the vulnerability of Docker images stored in ECR
Home-page: https://github.com/homoluctus/ecranner
License: MIT
Author: homoluctus
Author-email: w.slife18sy@gmail.com
Requires-Python: >=3.7,<4.0
Classifier: Development Status :: 4 - Beta
Classifier: Environment :: Console
Classifier: License :: OSI Approved :: MIT License
Classifier: Operating System :: MacOS
Classifier: Operating System :: POSIX :: Linux
Classifier: Operating System :: Unix
Classifier: Programming Language :: Python :: 3
Classifier: Programming Language :: Python :: 3 :: Only
Classifier: Programming Language :: Python :: 3.7
Requires-Dist: boto3 (>=1.9,<2.0)
Requires-Dist: docker (>=4.0,<5.0)
Requires-Dist: jsonschema (>=3.0,<4.0)
Requires-Dist: pyyaml (>=5.1,<6.0)
Requires-Dist: requests (>=2.22,<3.0)
Project-URL: Repository, https://github.com/homoluctus/ecranner
